[{"CommitteeId":"9","CommitteeName":"COUNCIL COMMITTEE","Description":"COUNCIL COMMITTEE","FolderPath":"COUNCIL COMMITTEE"},{"CommitteeId":"12","CommitteeName":"SECTION 80 LOCAL ECONOMIC DEVELOPMENT COMMITTEE","Description":"SECTION 80 LOCAL ECONOMIC DEVELOPMENT COMMITTEE","FolderPath":"SECTION 80 LOCAL ECONOMIC DEVELOPMENT COMMITTEE"},{"CommitteeId":"23","CommitteeName":"SECTION 79 SOCIAL SERVICES, YOUTH AND WOMEN DEVELOPMENT COMMITTEE MEETINGS","Description":"SECTION 79 SOCIAL SERVICES, YOUTH AND WOMEN DEVELOPMENT COMMITTEE MEETINGS","FolderPath":"SECTION 79 SOCIAL SERVICES, YOUTH AND WOMEN DEVELOPMENT COMMITTEE MEETINGS"},{"CommitteeId":"9","CommitteeName":"COUNCIL COMMITTEE","Description":"COUNCIL COMMITTEE","FolderPath":"COUNCIL COMMITTEE"}]